Workbook

Sheet Assumptions
A1: Driver | B1: Value
A2: Revenue growth | B2: 0.1
A3: Gross margin | B3: 0.42
A4: Opex % revenue | B4: 0.21
A5: Tax rate | B5: 0.27
A6: Capex % revenue | B6: 0.05
A7: Depreciation years | B7: 7
A8: DSO days | B8: 50
A9: Base revenue | B9: 120000

Sheet Income
A1: Line | B1: 2025 | C1: 2026 | D1: 2027 | E1: 2028 | F1: 2029 | G1: 2030 | H1: 2031 | I1: 2032 | J1: 2033 | K1: 2034
A2: Revenue | B2: =Assumptions!$B$9 -> 120000 | C2: =B2*(1+Growth) -> 132000 | D2: =C2*(1+Growth) -> 145200 | E2: =D2*(1+Growth) -> 159720 | F2: =E2*(1+Growth) -> 175692 | G2: =F2*(1+Growth) -> 193261.2 | H2: =G2*(1+Growth) -> 212587.32 | I2: =H2*(1+Growth) -> 233846.05 | J2: =I2*(1+Growth) -> 257230.66 | K2: =J2*(1+Growth) -> 282953.72
A3: COGS | B3: =-B2*(1-Assumptions!$B$3) -> -69600 | C3: =-C2*(1-Assumptions!$B$3) -> -76560 | D3: =-D2*(1-Assumptions!$B$3) -> -84216 | E3: =-E2*(1-Assumptions!$B$3) -> -92637.6 | F3: =-F2*(1-Assumptions!$B$3) -> -101901.36 | G3: =-G2*(1-Assumptions!$B$3) -> -112091.5 | H3: =-H2*(1-Assumptions!$B$3) -> -123300.65 | I3: =-I2*(1-Assumptions!$B$3) -> -135630.71 | ... K3: =-K2*(1-Assumptions!$B$3) -> -164113.16
A4: Gross profit | B4: =B2+B3 -> 50400 | C4: =C2+C3 -> 55440 | D4: =D2+D3 -> 60984 | E4: =E2+E3 -> 67082.4 | F4: =F2+F3 -> 73790.64 | G4: =G2+G3 -> 81169.704 | H4: =H2+H3 -> 89286.674 | I4: =I2+I3 -> 98215.342 | ... K4: =K2+K3 -> 118840.56
A5: Opex | B5: =-B2*Assumptions!$B$4 -> -25200 | C5: =-C2*Assumptions!$B$4 -> -27720 | D5: =-D2*Assumptions!$B$4 -> -30492 | E5: =-E2*Assumptions!$B$4 -> -33541.2 | F5: =-F2*Assumptions!$B$4 -> -36895.32 | G5: =-G2*Assumptions!$B$4 -> -40584.852 | H5: =-H2*Assumptions!$B$4 -> -44643.337 | I5: =-I2*Assumptions!$B$4 -> -49107.671 | ... K5: =-K2*Assumptions!$B$4 -> -59420.282
A6: EBITDA | B6: =B4+B5 -> 25200 | C6: =C4+C5 -> 27720 | D6: =D4+D5 -> 30492 | E6: =E4+E5 -> 33541.2 | F6: =F4+F5 -> 36895.32 | G6: =G4+G5 -> 40584.852 | H6: =H4+H5 -> 44643.337 | I6: =I4+I5 -> 49107.671 | ... K6: =K4+K5 -> 59420.282
A7: Depreciation | B7: =-Cash!B3/Assumptions!$B$7 -> -857.14286 | C7: =-SUM(Cash!$B$3:C3)/Assumptions!$B$7 -> -1800 | D7: =-SUM(Cash!$B$3:D3)/Assumptions!$B$7 -> -2837.1429 | E7: =-SUM(Cash!$B$3:E3)/Assumptions!$B$7 -> -3978 | F7: =-SUM(Cash!$B$3:F3)/Assumptions!$B$7 -> -5232.9429 | G7: =-SUM(Cash!$B$3:G3)/Assumptions!$B$7 -> -6613.38 | H7: =-SUM(Cash!$B$3:H3)/Assumptions!$B$7 -> -8131.8609 | I7: =-SUM(Cash!$B$3:I3)/Assumptions!$B$7 -> -9802.1898 | J7: =-SUM(Cash!$B$3:J3)/Assumptions!$B$7 -> -11639.552 | K7: =-SUM(Cash!$B$3:K3)/Assumptions!$B$7 -> -13660.65
A8: EBIT | B8: =B6+B7 -> 24342.857 | C8: =C6+C7 -> 25920 | D8: =D6+D7 -> 27654.857 | E8: =E6+E7 -> 29563.2 | F8: =F6+F7 -> 31662.377 | G8: =G6+G7 -> 33971.472 | H8: =H6+H7 -> 36511.476 | I8: =I6+I7 -> 39305.481 | ... K8: =K6+K7 -> 45759.632
A9: Tax | B9: =-MAX(0,B8)*TaxRate -> -6572.5714 | C9: =-MAX(0,C8)*TaxRate -> -6998.4 | D9: =-MAX(0,D8)*TaxRate -> -7466.8114 | E9: =-MAX(0,E8)*TaxRate -> -7982.064 | F9: =-MAX(0,F8)*TaxRate*1.1 -> -9403.726 | G9: =-MAX(0,G8)*TaxRate -> -9172.2974 | H9: =-MAX(0,H8)*TaxRate -> -9858.0986 | I9: =-MAX(0,I8)*TaxRate -> -10612.48 | J9: =-MAX(0,J8)*TaxRate -> -11442.299 | K9: =-MAX(0,K8)*TaxRate -> -12355.101
A10: Net income | B10: =B8+B9 -> 17770.286 | C10: =C8+C9 -> 18921.6 | D10: =D8+D9 -> 20188.046 | E10: =E8+E9 -> 21581.136 | F10: =F8+F9 -> 22258.651 | G10: =G8+G9 -> 24799.175 | H10: =H8+H9 -> 26653.378 | I10: =I8+I9 -> 28693.001 | ... K10: =K8+K9 -> 33404.531

Sheet Cash
A1: Line | B1: 2025 | C1: 2026 | D1: 2027 | E1: 2028 | F1: 2029 | G1: 2030 | H1: 2031 | I1: 2032 | J1: 2033 | K1: 2034
A2: Net income | B2: =Income!B10 -> 17770.286 | C2: =Income!C10 -> 18921.6 | D2: =Income!D10 -> 20188.046 | E2: =Income!E10 -> 21581.136 | F2: =Income!F10 -> 22258.651 | G2: =Income!G10 -> 24799.175 | H2: =Income!H10 -> 26653.378 | I2: =Income!I10 -> 28693.001 | ... K2: =Income!K10 -> 33404.531
A3: Capex | B3: =Income!B2*Assumptions!$B$6 -> 6000 | C3: =Income!C2*Assumptions!$B$6 -> 6600 | D3: =Income!D2*Assumptions!$B$6 -> 7260 | E3: =Income!E2*Assumptions!$B$6 -> 7986 | F3: =Income!F2*Assumptions!$B$6 -> 8784.6 | G3: =Income!G2*Assumptions!$B$6 -> 9663.06 | H3: =Income!H2*Assumptions!$B$6 -> 10629.366 | I3: =Income!I2*Assumptions!$B$6 -> 11692.303 | ... K3: =Income!K2*Assumptions!$B$6 -> 14147.686
A4: Receivables | B4: =Income!B2*Assumptions!$B$8/365 -> 16438.356 | C4: =Income!C2*Assumptions!$B$8/365 -> 18082.192 | D4: =Income!D2*Assumptions!$B$8/365 -> 19890.411 | E4: =Income!E2*Assumptions!$B$8/365 -> 21879.452 | F4: =Income!F2*Assumptions!$B$8/365 -> 24067.397 | G4: =Income!G2*Assumptions!$B$8/365 -> 26474.137 | H4: =Income!H2*Assumptions!$B$8/365 -> 29121.551 | I4: =Income!I2*Assumptions!$B$8/365 -> 32033.706 | ... K4: =Income!K2*Assumptions!$B$8/365 -> 38760.784
A5: Change in AR | B5: =B4 -> 16438.356 | C5: =C4-B4 -> 1643.8356 | D5: =D4-C4 -> 1808.2192 | E5: =E4-D4 -> 1989.0411 | F5: =F4-E4 -> 2187.9452 | G5: =G4-F4 -> 2406.7397 | H5: =H4-G4 -> 2647.4137 | I5: =I4-H4 -> 2912.1551 | J5: =J4-I4 -> 3203.3706 | K5: =K4-J4 -> 3523.7076
A6: Free cash flow | B6: =B2-B3-B5-Income!B7 -> -3810.9276 | C6: =C2-C3-C5-Income!C7 -> 12477.764 | D6: =D2-D3-D5-Income!D7 -> 13956.969 | E6: =E2-E3-E5-Income!E7 -> 15584.095 | F6: =F2-F3-F5-Income!F7 -> 16519.049 | G6: =G2-G3-G5-Income!G7 -> 19342.755 | H6: =H2-H3-H5-Income!H7 -> 21508.459 | I6: =I2-I3-I5-Income!I7 -> 23890.733 | ... K6: =K2-K3-K5-Income!K7 -> 29393.787
A7: Cumulative FCF | B7: =B6 -> -3810.9276 | C7: =B7+C6 -> 8666.8368 | D7: =C7+D6 -> 22623.806 | E7: =D7+E6 -> 38207.901 | F7: =E7+F6 -> 54726.95 | G7: =F7+G6 -> 74069.705 | H7: =G7+H6 -> 95578.164 | I7: =H7+I6 -> 119468.9 | J7: =I7+J6 -> 145980.13 | K7: =J7+K6 -> 175373.92

Sheet Summary
A1: Metric | B1: Value
A2: Total revenue | B2: =SUM(Income!B2:K2) -> 1912491
A3: Total net income | B3: =SUM(Income!B10:K10) -> 245206.39
A4: Avg net margin | B4: =B3/B2 -> 0.1282131
A5: Ending cash | B5: =Cash!K7 -> 175373.92
A6: Payback year | B6: =IFERROR(INDEX(Cash!B1:K1,MATCH(TRUE(),INDEX(Cash!B7:K7>0,0),0)),"never") -> 2026
A7: Margin flag | B7: =IF(B4>0.15,"healthy",IF(B4>0.05,"thin","loss")) -> thin
