Workbook

Sheet Products
A1: sku | B1: name | C1: price | D1: cost | E1: margin
A2: SKU-0000 | B2: Item 0 | C2: 188.76 | D2: 131.51 | E2: =(C2-D2)/C2
A3: SKU-0001 | B3: Item 1 | C3: 239.58 | D3: 186.15 | E3: =(C3-D3)/C3
A4: SKU-0002 | B4: Item 2 | C4: 223.27 | D4: 171.68 | E4: =(C4-D4)/C4
A5: SKU-0003 | B5: Item 3 | C5: 13.56 | D5: 7.95 | E5: =(C5-D5)/C5
A6: SKU-0004 | B6: Item 4 | C6: 283.29 | D6: 186.86 | E6: =(C6-D6)/C6
A7: SKU-0005 | B7: Item 5 | C7: 270.77 | D7: 120.57 | E7: =(C7-D7)/C7
A8: SKU-0006 | B8: Item 6 | C8: 143.38 | D8: 71.49 | E8: =(C8-D8)/C8
A9: SKU-0007 | B9: Item 7 | C9: 99 | D9: 104.14 | E9: =(C9-D9)/C9
A10: SKU-0008 | B10: Item 8 | C10: 8.87 | D10: 4.32 | E10: =(C10-D10)/C10
A11: SKU-0009 | B11: Item 9 | C11: 87.45 | D11: 67.03 | E11: =(C11-D11)/C11
A12: SKU-0010 | B12: Item 10 | C12: 230.89 | D12: 107.1 | E12: =(C12-D12)/C12
A13: SKU-0011 | B13: Item 11 | C13: 240.16 | D13: 109.39 | E13: =(C13-D13)/C13
... A201: SKU-0199 | B201: Item 199 | C201: 31.9 | D201: 14.35 | E201: =(C201-D201)/C201

Sheet Orders
A1: order | B1: sku | C1: qty | D1: unit price | E1: line total | F1: cost | G1: profit
A2: 50000 | B2: SKU-0152 | C2: 15 | D2: =VLOOKUP(B2,Products!$A$2:$D$201,3,FALSE()) | E2: =C2*D2 | F2: =C2*INDEX(Products!$D$2:$D$201,MATCH(B2,Products!$A$2:$A$201,0)) | G2: =E2-F2
A3: 50001 | B3: SKU-0061 | C3: 13 | D3: =VLOOKUP(B3,Products!$A$2:$D$201,3,FALSE()) | E3: =C3*D3 | F3: =C3*INDEX(Products!$D$2:$D$201,MATCH(B3,Products!$A$2:$A$201,0)) | G3: =E3-F3
A4: 50002 | B4: SKU-0118 | C4: 16 | D4: =VLOOKUP(B4,Products!$A$2:$D$201,3,FALSE()) | E4: =C4*D4 | F4: =C4*INDEX(Products!$D$2:$D$201,MATCH(B4,Products!$A$2:$A$201,0)) | G4: =E4-F4
A5: 50003 | B5: SKU-0082 | C5: 4 | D5: =VLOOKUP(B5,Products!$A$2:$D$201,3,FALSE()) | E5: =C5*D5 | F5: =C5*INDEX(Products!$D$2:$D$201,MATCH(B5,Products!$A$2:$A$201,0)) | G5: =E5-F5
A6: 50004 | B6: SKU-0135 | C6: 1 | D6: =VLOOKUP(B6,Products!$A$2:$D$201,3,FALSE()) | E6: =C6*D6 | F6: =C6*INDEX(Products!$D$2:$D$201,MATCH(B6,Products!$A$2:$A$201,0)) | G6: =E6-F6
A7: 50005 | B7: SKU-0138 | C7: 13 | D7: =VLOOKUP(B7,Products!$A$2:$D$201,3,FALSE()) | E7: =C7*D7 | F7: =C7*INDEX(Products!$D$2:$D$201,MATCH(B7,Products!$A$2:$A$201,0)) | G7: =E7-F7
A8: 50006 | B8: SKU-0013 | C8: 5 | D8: =VLOOKUP(B8,Products!$A$2:$D$201,3,FALSE()) | E8: =C8*D8 | F8: =C8*INDEX(Products!$D$2:$D$201,MATCH(B8,Products!$A$2:$A$201,0)) | G8: =E8-F8
A9: 50007 | B9: SKU-0109 | C9: 8 | D9: =VLOOKUP(B9,Products!$A$2:$D$201,3,FALSE()) | E9: =C9*D9 | F9: =C9*INDEX(Products!$D$2:$D$201,MATCH(B9,Products!$A$2:$A$201,0)) | G9: =E9-F9
A10: 50008 | B10: SKU-0191 | C10: 4 | D10: =VLOOKUP(B10,Products!$A$2:$D$201,3,FALSE()) | E10: =C10*D10 | F10: =C10*INDEX(Products!$D$2:$D$201,MATCH(B10,Products!$A$2:$A$201,0)) | G10: =E10-F10
A11: 50009 | B11: SKU-0021 | C11: 16 | D11: =VLOOKUP(B11,Products!$A$2:$D$201,3,FALSE()) | E11: =C11*D11 | F11: =C11*INDEX(Products!$D$2:$D$201,MATCH(B11,Products!$A$2:$A$201,0)) | G11: =E11-F11
A12: 50010 | B12: SKU-0054 | C12: 5 | D12: =VLOOKUP(B12,Products!$A$2:$D$201,3,FALSE()) | E12: =C12*D12 | F12: =C12*INDEX(Products!$D$2:$D$201,MATCH(B12,Products!$A$2:$A$201,0)) | G12: =E12-F12
A13: 50011 | B13: SKU-0179 | C13: 20 | D13: =VLOOKUP(B13,Products!$A$2:$D$201,3,FALSE()) | E13: =C13*D13 | F13: =C13*INDEX(Products!$D$2:$D$201,MATCH(B13,Products!$A$2:$A$201,0)) | G13: =E13-F13
... A2501: 52499 | B2501: SKU-0060 | C2501: 13 | D2501: =VLOOKUP(B2501,Products!$A$2:$D$201,3,FALSE()) | E2501: =C2501*D2501 | F2501: =C2501*INDEX(Products!$D$2:$D$201,MATCH(B2501,Products!$A$2:$A$201,0)) | G2501: =E2501-F2501

Sheet Report
A1: metric | B1: value
A2: Revenue | B2: =SUM(Orders!E2:E2501)
A3: Profit | B3: =SUM(Orders!G2:G2501)
A4: Margin | B4: =ROUND(B3/B2,4)
A5: Top SKU units | B5: =MAX(Orders!C2:C2501)
A6: SKU-0007 revenue | B6: =SUMIF(Orders!B2:B2501,"SKU-0007",Orders!E2:E2501)
A7: Orders > 1000 | B7: =COUNTIF(Orders!E2:E2501,">1000")
